xaas/__init__.py
xaas/cli.py
xaas-0.0.0.dist-info/METADATA
xaas-0.0.0.dist-info/WHEEL
xaas-0.0.0.dist-info/entry_points.txt
xaas-0.0.0.dist-info/licenses/LICENSE
xaas-0.0.0.dist-info/RECORD
